aiida_fans/__init__.py
aiida_fans/_version.py
aiida_fans/calculations.py
aiida_fans/helpers.py
aiida_fans/parsers.py
aiida_fans/utils.py
aiida_fans-0.2.1.dist-info/licenses/LICENSE
aiida_fans-0.2.1.dist-info/METADATA
aiida_fans-0.2.1.dist-info/WHEEL
aiida_fans-0.2.1.dist-info/entry_points.txt
aiida_fans-0.2.1.dist-info/top_level.txt
aiida_fans-0.2.1.dist-info/RECORD
