Metadata-Version: 2.4
Name: aiida-fans
Version: 0.2.1
Summary: AiiDA plugin for FANS, an FFT-based homogenization solver.
Author-email: Ethan Shanahan <ethan.shanahan@gmail.com>
License-Expression: LGPL-3.0-or-later
Project-URL: Documentation, http://aiida-fans.readthedocs.io/en/latest/
Project-URL: Source, https://github.com/ethan-shanahan/aiida-fans
Keywords: aiida,fans,plugin
Classifier: Natural Language :: English
Classifier: Programming Language :: Python
Classifier: Operating System :: POSIX :: Linux
Classifier: Intended Audience :: Science/Research
Classifier: Development Status :: 3 - Alpha
Classifier: Framework :: AiiDA
Requires-Python: >=3.11
License-File: LICENSE
Requires-Dist: aiida-core>=2.6
Requires-Dist: h5py
Dynamic: license-file
